{"user": "dustin.c@zer0p1k4chugmail.onmicrosoft.com", "name": "poniard-logger", "type": "user", "rg": ""}
{"user": "mysql-reader", "name": "headset-directory", "type": "msi", "rg": "mygroup_1"}
{"user": "judy.v@zer0p1k4chugmail.onmicrosoft.com", "name": "headset-directory", "type": "user", "rg": ""}
{"user": "mysql-reader", "name": "unpurse-server", "type": "msi", "rg": "mygroup_1"}
{"user": "derek.k@zer0p1k4chugmail.onmicrosoft.com", "name": "poniard-logger", "type": "user", "rg": ""}
{"user": "postgresql-owner", "name": "unpurse-server", "type": "msi", "rg": "mygroup_1"}
{"user": "amy.r@zer0p1k4chugmail.onmicrosoft.com", "name": "poniard-logger", "type": "user", "rg": ""}
{"user": "postgresql-owner", "name": "poniard-logger", "type": "msi", "rg": "mygroup_1"}
{"user": "kimberly.t@zer0p1k4chugmail.onmicrosoft.com", "name": "headset-directory", "type": "user", "rg": ""}
{"user": "dev-owner", "name": "unpurse-server", "type": "msi", "rg": "mygroup_3"}
